Metadata-Version: 2.1
Name: random-dict
Version: 1.1.0
Summary: Simple python package to generate random dictionaries of given types.
Home-page: https://github.com/LucaCappelletti94/random_dict
Author: Luca Cappelletti
Author-email: cappelletti.luca94@gmail.com
License: MIT
Platform: UNKNOWN
Classifier: Development Status :: 5 - Production/Stable
Classifier: License :: OSI Approved :: MIT License
Classifier: Programming Language :: Python :: 3
Provides-Extra: test
License-File: LICENSE
